{"version":1,"sessions":{"d796bcf5-9edd-40c9-a7e8-d39f204215e2":{"updatedAt":1782706665497,"files":{"C:\\Users\\jnorv\\copilot-worktrees\\scrap-app\\jnorvi5-symmetrical-adventure\\server\\src\\yards.ts":{"editCount":3,"findings":[]},"C:\\Users\\jnorv\\copilot-worktrees\\scrap-app\\jnorvi5-symmetrical-adventure\\mobile\\components\\YardMapView.tsx":{"editCount":1,"findings":[]},"C:\\Users\\jnorv\\copilot-worktrees\\scrap-app\\jnorvi5-symmetrical-adventure\\server\\src\\routers\\scrap.ts":{"editCount":4,"findings":[]},"C:\\Users\\jnorv\\copilot-worktrees\\scrap-app\\jnorvi5-symmetrical-adventure\\mobile\\screens\\YardComparison.tsx":{"editCount":6,"findings":[]},"C:\\Users\\jnorv\\copilot-worktrees\\scrap-app\\jnorvi5-symmetrical-adventure\\web\\index.html":{"editCount":1,"findings":["single-font:85","em-dash-overuse:0:10 em-dashes in body text","dark-glow:294"]},"C:\\Users\\jnorv\\copilot-worktrees\\scrap-app\\jnorvi5-symmetrical-adventure\\server\\src\\schema.ts":{"editCount":1,"findings":[]},"C:\\Users\\jnorv\\copilot-worktrees\\scrap-app\\jnorvi5-symmetrical-adventure\\drizzle\\schema.ts":{"editCount":1,"findings":[]},"C:\\Users\\jnorv\\copilot-worktrees\\scrap-app\\jnorvi5-symmetrical-adventure\\server\\src\\trpc.ts":{"editCount":1,"findings":[]},"C:\\Users\\jnorv\\copilot-worktrees\\scrap-app\\jnorvi5-symmetrical-adventure\\server\\src\\priceReports.ts":{"editCount":1,"findings":[]},"C:\\Users\\jnorv\\copilot-worktrees\\scrap-app\\jnorvi5-symmetrical-adventure\\server\\src\\routers\\yards.ts":{"editCount":1,"findings":[]},"C:\\Users\\jnorv\\copilot-worktrees\\scrap-app\\jnorvi5-symmetrical-adventure\\server\\src\\routers\\_app.ts":{"editCount":1,"findings":[]}}}}}